llama_index/graph_stores/tidb/__init__.py
llama_index/graph_stores/tidb/graph.py
llama_index/graph_stores/tidb/property_graph.py
llama_index/graph_stores/tidb/utils.py
llama_index_graph_stores_tidb-0.4.1.dist-info/METADATA
llama_index_graph_stores_tidb-0.4.1.dist-info/WHEEL
llama_index_graph_stores_tidb-0.4.1.dist-info/licenses/LICENSE
llama_index_graph_stores_tidb-0.4.1.dist-info/RECORD
