Metadata-Version: 2.4
Name: llama-index-graph-stores-tidb
Version: 0.4.1
Summary: llama-index graph stores tidb integration
Author-email: Your Name <you@example.com>
License-Expression: MIT
License-File: LICENSE
Requires-Python: <4.0,>=3.9
Requires-Dist: llama-index-core<0.15,>=0.13.0
Requires-Dist: pymysql<2,>=1.1.1
Requires-Dist: sqlalchemy<3,>=2.0.30
Requires-Dist: tidb-vector<0.0.10,>=0.0.9
